{
  "_fv": 77,
  "_type": "recipe",
  "definition": {
    "recipeType": "Crafting",
    "recipeRetstackSize": 3,
    "group": "wooden_door",
    "cookingBookCategory": "MISC",
    "xpReward": 0.0,
    "cookingTime": 200,
    "craftingBookCategory": "BUILDING",
    "recipeShapeless": false,
    "recipeSlots": [
      {
        "value": "CUSTOM:PalmPlanks"
      },
      {
        "value": "CUSTOM:PalmPlanks"
      },
      {
        "value": ""
      },
      {
        "value": "CUSTOM:PalmPlanks"
      },
      {
        "value": "CUSTOM:PalmPlanks"
      },
      {
        "value": ""
      },
      {
        "value": "CUSTOM:PalmPlanks"
      },
      {
        "value": "CUSTOM:PalmPlanks"
      },
      {
        "value": ""
      }
    ],
    "recipeReturnStack": {
      "value": "CUSTOM:PalmDoor"
    },
    "name": "palm_door_recipe",
    "namespace": "mod"
  }
}